Flask_JWT_RFC7519-1.0.5.dist-info/LICENSE.txt
Flask_JWT_RFC7519-1.0.5.dist-info/METADATA
Flask_JWT_RFC7519-1.0.5.dist-info/RECORD
Flask_JWT_RFC7519-1.0.5.dist-info/WHEEL
Flask_JWT_RFC7519-1.0.5.dist-info/top_level.txt
flask_jwt_rfc7519/__init__.py
flask_jwt_rfc7519/config.py
flask_jwt_rfc7519/default_callbacks.py
flask_jwt_rfc7519/exceptions.py
flask_jwt_rfc7519/jwt_manager.py
flask_jwt_rfc7519/tokens.py
flask_jwt_rfc7519/utils.py
flask_jwt_rfc7519/view_decorators.py
