Metadata-Version: 2.1
Name: Flask-JWT-RFC7519
Version: 1.0.5
Summary: FLASK JWT implementing the RFC7519 proposed standard
Home-page: UNKNOWN
Author: Magnus Hartvig Groenbech
Author-email: groenbech96@gmail.com
License: MIT
Keywords: flask,jwt,json web token
Platform: any
Classifier: Development Status :: 5 - Production/Stable
Classifier: Environment :: Web Environment
Classifier: Intended Audience :: Developers
Classifier: License :: OSI Approved :: MIT License
Classifier: Operating System :: OS Independent
Classifier: Programming Language :: Python
Classifier: Programming Language :: Python :: 2.7
Classifier: Programming Language :: Python :: 3
Classifier: Programming Language :: Python :: 3.4
Classifier: Programming Language :: Python :: 3.5
Classifier: Programming Language :: Python :: 3.6
Classifier: Topic :: Internet :: WWW/HTTP :: Dynamic Content
Classifier: Topic :: Software Development :: Libraries :: Python Modules
Requires-Dist: Werkzeug (>=0.14)
Requires-Dist: Flask
Requires-Dist: PyJWT (>=1.6.0)
Requires-Dist: cryptography
